lsdb/__init__.py
lsdb/_version.py
lsdb/py.typed
lsdb/types.py
lsdb/catalog/__init__.py
lsdb/catalog/association_catalog.py
lsdb/catalog/catalog.py
lsdb/catalog/map_catalog.py
lsdb/catalog/margin_catalog.py
lsdb/catalog/dataset/__init__.py
lsdb/catalog/dataset/healpix_dataset.py
lsdb/core/__init__.py
lsdb/core/crossmatch/__init__.py
lsdb/core/crossmatch/abstract_crossmatch_algorithm.py
lsdb/core/crossmatch/crossmatch.py
lsdb/core/crossmatch/crossmatch_args.py
lsdb/core/crossmatch/kdtree_match.py
lsdb/core/crossmatch/kdtree_utils.py
lsdb/core/plotting/__init__.py
lsdb/core/plotting/plot_points.py
lsdb/core/search/__init__.py
lsdb/core/search/abstract_search.py
lsdb/core/search/index_search.py
lsdb/core/search/region_search.py
lsdb/dask/__init__.py
lsdb/dask/concat_catalog_data.py
lsdb/dask/crossmatch_catalog_data.py
lsdb/dask/divisions.py
lsdb/dask/join_catalog_data.py
lsdb/dask/merge_catalog_functions.py
lsdb/dask/merge_map_catalog_data.py
lsdb/dask/partition_indexer.py
lsdb/io/__init__.py
lsdb/io/common.py
lsdb/io/schema.py
lsdb/io/to_association.py
lsdb/io/to_collection.py
lsdb/io/to_hats.py
lsdb/loaders/__init__.py
lsdb/loaders/dataframe/__init__.py
lsdb/loaders/dataframe/dataframe_catalog_loader.py
lsdb/loaders/dataframe/from_astropy.py
lsdb/loaders/dataframe/from_dataframe.py
lsdb/loaders/dataframe/from_dataframe_utils.py
lsdb/loaders/dataframe/margin_catalog_generator.py
lsdb/loaders/hats/__init__.py
lsdb/loaders/hats/hats_loading_config.py
lsdb/loaders/hats/read_hats.py
lsdb/nested/__init__.py
lsdb/nested/accessor.py
lsdb/nested/backends.py
lsdb/nested/core.py
lsdb/nested/py.typed
lsdb/nested/datasets/__init__.py
lsdb/nested/datasets/generation.py
lsdb/nested/utils/__init__.py
lsdb/nested/utils/utils.py
lsdb-0.8.1.dist-info/licenses/CITATION.bib
lsdb-0.8.1.dist-info/licenses/LICENSE
lsdb-0.8.1.dist-info/METADATA
lsdb-0.8.1.dist-info/WHEEL
lsdb-0.8.1.dist-info/top_level.txt
lsdb-0.8.1.dist-info/RECORD
