Metadata-Version: 2.4
Name: lsdb
Version: 0.8.1
Summary: Spatial analysis for extremely large astronomical catalogs using dask
Author-email: LINCC Frameworks <lincc-frameworks-team@lists.lsst.org>
License-Expression: BSD-3-Clause
Project-URL: source, https://github.com/astronomy-commons/lsdb
Project-URL: documentation, https://lsdb.readthedocs.io/
Classifier: Development Status :: 4 - Beta
Classifier: Intended Audience :: Developers
Classifier: Intended Audience :: Science/Research
Classifier: Operating System :: OS Independent
Classifier: Programming Language :: Python
Requires-Python: >=3.11
License-File: LICENSE
License-File: CITATION.bib
Requires-Dist: dask[complete]>=2025.3.0
Requires-Dist: deprecated
Requires-Dist: hats<0.9,>=0.8
Requires-Dist: nested-pandas<0.7.0,>=0.6.7
Requires-Dist: numpy
Requires-Dist: pyarrow
Requires-Dist: scipy>=1.7.2
Requires-Dist: tabulate>=0.7.0
Requires-Dist: universal-pathlib
Provides-Extra: dev
Requires-Dist: asv[virtualenv]==0.6.5; extra == "dev"
Requires-Dist: astropy; extra == "dev"
Requires-Dist: black; extra == "dev"
Requires-Dist: jupyter; extra == "dev"
Requires-Dist: mypy; extra == "dev"
Requires-Dist: pre-commit; extra == "dev"
Requires-Dist: pylint; extra == "dev"
Requires-Dist: pytest; extra == "dev"
Requires-Dist: pytest-cov; extra == "dev"
Requires-Dist: pytest-mock; extra == "dev"
Requires-Dist: types-tabulate; extra == "dev"
Provides-Extra: s3fs
Requires-Dist: s3fs>0.5; extra == "s3fs"
Provides-Extra: full
Requires-Dist: fsspec[full]; extra == "full"
Requires-Dist: ipykernel; extra == "full"
Requires-Dist: ipywidgets; extra == "full"
Requires-Dist: lsst-sphgeom; (sys_platform == "darwin" or sys_platform == "linux") and extra == "full"
Requires-Dist: matplotlib; extra == "full"
Dynamic: license-file
